{"nodes": [{"id": "game_engine_powerhouse_js", "label": "powerhouse.js", "file_type": "code", "source_file": "game_engine/powerhouse.js", "source_location": "L1"}, {"id": "powerhouse_selectpowerhouse", "label": "selectPowerHouse()", "file_type": "code", "source_file": "game_engine/powerhouse.js", "source_location": "L8"}, {"id": "powerhouse_selectpartnercards", "label": "selectPartnerCards()", "file_type": "code", "source_file": "game_engine/powerhouse.js", "source_location": "L31"}, {"id": "powerhouse_getpartnercardcount", "label": "getPartnerCardCount()", "file_type": "code", "source_file": "game_engine/powerhouse.js", "source_location": "L121"}, {"id": "powerhouse_determineteams", "label": "determineTeams()", "file_type": "code", "source_file": "game_engine/powerhouse.js", "source_location": "L138"}, {"id": "powerhouse_checkpartnerreveal", "label": "checkPartnerReveal()", "file_type": "code", "source_file": "game_engine/powerhouse.js", "source_location": "L158"}], "edges": [{"source": "game_engine_powerhouse_js", "target": "powerhouse_selectpowerhouse", "relation": "contains", "confidence": "EXTRACTED", "source_file": "game_engine/powerhouse.js", "source_location": "L8", "weight": 1.0}, {"source": "game_engine_powerhouse_js", "target": "powerhouse_selectpartnercards", "relation": "contains", "confidence": "EXTRACTED", "source_file": "game_engine/powerhouse.js", "source_location": "L31", "weight": 1.0}, {"source": "game_engine_powerhouse_js", "target": "powerhouse_getpartnercardcount", "relation": "contains", "confidence": "EXTRACTED", "source_file": "game_engine/powerhouse.js", "source_location": "L121", "weight": 1.0}, {"source": "game_engine_powerhouse_js", "target": "powerhouse_determineteams", "relation": "contains", "confidence": "EXTRACTED", "source_file": "game_engine/powerhouse.js", "source_location": "L138", "weight": 1.0}, {"source": "game_engine_powerhouse_js", "target": "powerhouse_checkpartnerreveal", "relation": "contains", "confidence": "EXTRACTED", "source_file": "game_engine/powerhouse.js", "source_location": "L158", "weight": 1.0}, {"source": "powerhouse_selectpartnercards", "target": "powerhouse_getpartnercardcount", "relation": "calls", "confidence": "EXTRACTED", "source_file": "game_engine/powerhouse.js", "source_location": "L37", "weight": 1.0}], "raw_calls": [{"caller_nid": "powerhouse_selectpowerhouse", "callee": "includes", "source_file": "game_engine/powerhouse.js", "source_location": "L13"}, {"caller_nid": "powerhouse_selectpartnercards", "callee": "filter", "source_file": "game_engine/powerhouse.js", "source_location": "L48"}, {"caller_nid": "powerhouse_selectpartnercards", "callee": "find", "source_file": "game_engine/powerhouse.js", "source_location": "L63"}, {"caller_nid": "powerhouse_selectpartnercards", "callee": "includes", "source_file": "game_engine/powerhouse.js", "source_location": "L66"}, {"caller_nid": "powerhouse_selectpartnercards", "callee": "map", "source_file": "game_engine/powerhouse.js", "source_location": "L82"}, {"caller_nid": "powerhouse_selectpartnercards", "callee": "log", "source_file": "game_engine/powerhouse.js", "source_location": "L105"}, {"caller_nid": "powerhouse_selectpartnercards", "callee": "substring", "source_file": "game_engine/powerhouse.js", "source_location": "L105"}, {"caller_nid": "powerhouse_selectpartnercards", "callee": "stringify", "source_file": "game_engine/powerhouse.js", "source_location": "L105"}, {"caller_nid": "powerhouse_selectpartnercards", "callee": "log", "source_file": "game_engine/powerhouse.js", "source_location": "L106"}, {"caller_nid": "powerhouse_selectpartnercards", "callee": "stringify", "source_file": "game_engine/powerhouse.js", "source_location": "L106"}, {"caller_nid": "powerhouse_selectpartnercards", "callee": "log", "source_file": "game_engine/powerhouse.js", "source_location": "L107"}, {"caller_nid": "powerhouse_selectpartnercards", "callee": "stringify", "source_file": "game_engine/powerhouse.js", "source_location": "L107"}, {"caller_nid": "powerhouse_checkpartnerreveal", "callee": "some", "source_file": "game_engine/powerhouse.js", "source_location": "L163"}, {"caller_nid": "powerhouse_checkpartnerreveal", "callee": "log", "source_file": "game_engine/powerhouse.js", "source_location": "L168"}, {"caller_nid": "powerhouse_checkpartnerreveal", "callee": "substring", "source_file": "game_engine/powerhouse.js", "source_location": "L168"}, {"caller_nid": "powerhouse_checkpartnerreveal", "callee": "log", "source_file": "game_engine/powerhouse.js", "source_location": "L172"}, {"caller_nid": "powerhouse_checkpartnerreveal", "callee": "reduce", "source_file": "game_engine/powerhouse.js", "source_location": "L178"}, {"caller_nid": "powerhouse_checkpartnerreveal", "callee": "filter", "source_file": "game_engine/powerhouse.js", "source_location": "L178"}, {"caller_nid": "powerhouse_checkpartnerreveal", "callee": "log", "source_file": "game_engine/powerhouse.js", "source_location": "L183"}, {"caller_nid": "powerhouse_checkpartnerreveal", "callee": "cardsMatch", "source_file": "game_engine/powerhouse.js", "source_location": "L188"}, {"caller_nid": "powerhouse_checkpartnerreveal", "callee": "cardsMatch", "source_file": "game_engine/powerhouse.js", "source_location": "L206"}, {"caller_nid": "powerhouse_checkpartnerreveal", "callee": "log", "source_file": "game_engine/powerhouse.js", "source_location": "L221"}, {"caller_nid": "powerhouse_checkpartnerreveal", "callee": "join", "source_file": "game_engine/powerhouse.js", "source_location": "L221"}, {"caller_nid": "powerhouse_checkpartnerreveal", "callee": "map", "source_file": "game_engine/powerhouse.js", "source_location": "L221"}, {"caller_nid": "powerhouse_checkpartnerreveal", "callee": "log", "source_file": "game_engine/powerhouse.js", "source_location": "L224"}, {"caller_nid": "powerhouse_checkpartnerreveal", "callee": "substring", "source_file": "game_engine/powerhouse.js", "source_location": "L224"}, {"caller_nid": "powerhouse_checkpartnerreveal", "callee": "includes", "source_file": "game_engine/powerhouse.js", "source_location": "L232"}, {"caller_nid": "powerhouse_checkpartnerreveal", "callee": "push", "source_file": "game_engine/powerhouse.js", "source_location": "L233"}, {"caller_nid": "powerhouse_checkpartnerreveal", "callee": "filter", "source_file": "game_engine/powerhouse.js", "source_location": "L236"}, {"caller_nid": "powerhouse_checkpartnerreveal", "callee": "log", "source_file": "game_engine/powerhouse.js", "source_location": "L252"}]}